raven_preprocess/__init__.py
raven_preprocess/col_info_constants.py
raven_preprocess/column_info.py
raven_preprocess/custom_statistics_util.py
raven_preprocess/data_source_info.py
raven_preprocess/dataset_level_info_util.py
raven_preprocess/file_format_constants.py
raven_preprocess/file_format_util.py
raven_preprocess/format_parser.py
raven_preprocess/msg_util.py
raven_preprocess/np_json_encoder.py
raven_preprocess/plot_values.py
raven_preprocess/preprocess.py
raven_preprocess/preprocess_runner.py
raven_preprocess/scratch_work.py
raven_preprocess/summary_stats_util.py
raven_preprocess/test_dataverse.py
raven_preprocess/type_guess_util.py
raven_preprocess/update_constants.py
raven_preprocess/variable_display_util.py
raven_preprocess/version_number_util.py
raven_preprocess/basic_utils/__init__.py
raven_preprocess/basic_utils/basic_err_check.py
raven_preprocess/basic_utils/basic_response.py
tworavens_preprocess-1.1.5.dist-info/LICENSE
tworavens_preprocess-1.1.5.dist-info/METADATA
tworavens_preprocess-1.1.5.dist-info/WHEEL
tworavens_preprocess-1.1.5.dist-info/top_level.txt
tworavens_preprocess-1.1.5.dist-info/RECORD
