Metadata-Version: 2.1
Name: tworavens-preprocess
Version: 1.1.5
Summary: TwoRavens Preprocess package
Home-page: https://github.com/TwoRavens/raven-metadata-service
Author: Two Ravens Team
Author-email: raman_prasad@harvard.edu
License: UNKNOWN
Keywords: tworavens preprocess metadata
Platform: UNKNOWN
Classifier: Development Status :: 5 - Production/Stable
Classifier: Intended Audience :: Developers
Classifier: Topic :: Software Development :: Build Tools
Classifier: License :: OSI Approved :: MIT License
Classifier: Programming Language :: Python :: 3.6
Classifier: Programming Language :: Python :: 3.7
Classifier: Programming Language :: Python :: 3.8
Classifier: Programming Language :: Python :: 3.9
Requires-Python: >=3.6
Requires-Dist: pandas (>=0.22.0)
Requires-Dist: scipy (>=1.4.1)
Requires-Dist: simplejson (>=3.13.2)
Requires-Dist: dictdiffer (==0.8.1)
Requires-Dist: requests (>=2.20.0)
Requires-Dist: numpy (>=1.18.2)
Requires-Dist: xlrd (>=1.1.0)
Requires-Dist: jsonschema (>=2.6.0)
Requires-Dist: pycountry (==19.8.18)
Requires-Dist: us (==1.0.0)
